emporium/__init__.py
emporium/base.py
emporium/cached.py
emporium/factory.py
emporium/utils.py
emporium/implementations/__init__.py
emporium/implementations/gcs.py
emporium/implementations/local.py
emporium/implementations/memory.py
emporium/implementations/s3.py
emporium-0.14.1.dist-info/METADATA
emporium-0.14.1.dist-info/WHEEL
emporium-0.14.1.dist-info/entry_points.txt
emporium-0.14.1.dist-info/RECORD
