Metadata-Version: 2.4
Name: emporium
Version: 0.14.1
Summary: Abstraction around different types of file stores.
Project-URL: Homepage, https://gitlab.com/greenhousegroup/ai/libraries/emporium/
Author-email: Marketing Engineering <bart.frenk@groupm.com>
License: MIT
Keywords: file-storage
Requires-Python: >=3.10
Requires-Dist: boto3<3.0.0,>=1.0.0
Requires-Dist: gcsfs>=0.4.0
Requires-Dist: setuptools>=75.3.0
Requires-Dist: smart-open>=1.8
Provides-Extra: docs
Requires-Dist: sphinx-rtd-theme>=3.0.1; extra == 'docs'
Requires-Dist: sphinx>=8.1.3; extra == 'docs'
Provides-Extra: test
Requires-Dist: faker>=30.8.2; extra == 'test'
Requires-Dist: mock>=5.1.0; extra == 'test'
Requires-Dist: pyright>=1.1.388; extra == 'test'
Requires-Dist: pytest>=8.3.3; extra == 'test'
